{
  "delegation": {
    "name": "قليبية",
    "code": "57"
  },
  "circonscription": {
    "name": "نابل 1",
    "code": "151"
  },
  "bureau_vote": {
    "name": "قاعة 4",
    "code": "04"
  },
  "centre_vote": {
    "name": "م إبتدائية سيدي احمد - قليبية الشرقية",
    "code": "009"
  },
  "resultat": {
    "listes": [
      {
        "num": 28,
        "pourcentage": 1.2300000190734863,
        "vote": 8,
        "name": "قائمة حزب تونس الخضراء"
      },
      {
        "num": 1,
        "pourcentage": 11.380000114440918,
        "vote": 74,
        "name": "قائمة حزب التكتل الديمقراطي من أجل العمل والحريات"
      },
      {
        "num": 29,
        "pourcentage": 2.4600000381469727,
        "vote": 16,
        "name": "قائمة حزب العمال الشيوعي التونسي (البديل الثوري)"
      },
      {
        "num": 2,
        "pourcentage": 0.46000000834465027,
        "vote": 3,
        "name": "قائمة الشعب يريد"
      },
      {
        "num": 30,
        "pourcentage": 1.2300000190734863,
        "vote": 8,
        "name": "قائمة الحركة الإصلاحية التونسية"
      },
      {
        "num": 3,
        "pourcentage": 3.380000114440918,
        "vote": 22,
        "name": "قائمة العريضة الشعبية للحرية والعدالة والتنمية"
      },
      {
        "num": 31,
        "pourcentage": 3.5399999618530273,
        "vote": 23,
        "name": "قائمة حزب الحرية والتنمية"
      },
      {
        "num": 4,
        "pourcentage": 0.6200000047683716,
        "vote": 4,
        "name": "قائمة الحزب الليبرالي المغاربي"
      },
      {
        "num": 32,
        "pourcentage": 0.3100000023841858,
        "vote": 2,
        "name": "قائمة حركة البعث"
      },
      {
        "num": 5,
        "pourcentage": 0,
        "vote": 0,
        "name": "قائمة حركة الوحدة الشعبية"
      },
      {
        "num": 33,
        "pourcentage": 0,
        "vote": 0,
        "name": "قائمة حركة الوطنيون الديمقراطيون"
      },
      {
        "num": 6,
        "pourcentage": 0.6200000047683716,
        "vote": 4,
        "name": "قائمة حركة الديمقراطيين الاشتراكيين"
      },
      {
        "num": 34,
        "pourcentage": 0.3100000023841858,
        "vote": 2,
        "name": "قائمة الائتلاف الديمقراطي المستقل - طريق السلامة -"
      },
      {
        "num": 7,
        "pourcentage": 0.15000000596046448,
        "vote": 1,
        "name": "قائمة نجاح الثورة"
      },
      {
        "num": 35,
        "pourcentage": 0.6200000047683716,
        "vote": 4,
        "name": "قائمة كلنا من أجل تونس"
      },
      {
        "num": 8,
        "pourcentage": 3.2300000190734863,
        "vote": 21,
        "name": "قائمة القطب الديمقراطي الحداثي"
      },
      {
        "num": 36,
        "pourcentage": 0.15000000596046448,
        "vote": 1,
        "name": "قائمة الائتلاف التحرري"
      },
      {
        "num": 9,
        "pourcentage": 0.3100000023841858,
        "vote": 2,
        "name": "قائمة الاتحاد الديمقراطي الوحدوي"
      },
      {
        "num": 37,
        "pourcentage": 0.3100000023841858,
        "vote": 2,
        "name": "قائمة المستقلين الأحرار"
      },
      {
        "num": 10,
        "pourcentage": 0.7699999809265137,
        "vote": 5,
        "name": "قائمة حزب اليسار الحديث"
      },
      {
        "num": 38,
        "pourcentage": 2.4600000381469727,
        "vote": 16,
        "name": "قائمة حزب آفاق تونس"
      },
      {
        "num": 11,
        "pourcentage": 0,
        "vote": 0,
        "name": "القائمة المستقلة من أجل جبهة وطنية"
      },
      {
        "num": 39,
        "pourcentage": 0.3100000023841858,
        "vote": 2,
        "name": "قائمة النور المستقلة"
      },
      {
        "num": 12,
        "pourcentage": 0.15000000596046448,
        "vote": 1,
        "name": "قائمة الحزب الديمقراطي للعدالة والرخاء"
      },
      {
        "num": 40,
        "pourcentage": 0.3100000023841858,
        "vote": 2,
        "name": "قائمة حزب الوفاق الجمهوري"
      },
      {
        "num": 13,
        "pourcentage": 0.9200000166893005,
        "vote": 6,
        "name": "قائمة الشباب الأحرار"
      },
      {
        "num": 41,
        "pourcentage": 0.15000000596046448,
        "vote": 1,
        "name": "قائمة إرادة شعب"
      },
      {
        "num": 14,
        "pourcentage": 0.9200000166893005,
        "vote": 6,
        "name": "قائمة الحزب الشعبي للحرية والتقدم"
      },
      {
        "num": 42,
        "pourcentage": 13.380000114440918,
        "vote": 87,
        "name": "قائمة حزب المؤتمر من أجل الجمهورية"
      },
      {
        "num": 15,
        "pourcentage": 0.9200000166893005,
        "vote": 6,
        "name": "قائمة حزب العمل التونسي"
      },
      {
        "num": 43,
        "pourcentage": 1.0800000429153442,
        "vote": 7,
        "name": "قائمة حزب الوحدة الشعبية"
      },
      {
        "num": 16,
        "pourcentage": 0.6200000047683716,
        "vote": 4,
        "name": "قائمة النضال الاجتماعي"
      },
      {
        "num": 44,
        "pourcentage": 0.3100000023841858,
        "vote": 2,
        "name": "قائمة الاعتــدال"
      },
      {
        "num": 17,
        "pourcentage": 0.15000000596046448,
        "vote": 1,
        "name": "قائمة عيون حريصة"
      },
      {
        "num": 45,
        "pourcentage": 35.689998626708984,
        "vote": 232,
        "name": "قائمة حركة النهضة"
      },
      {
        "num": 18,
        "pourcentage": 0,
        "vote": 0,
        "name": "قائمة حركة الشعب"
      },
      {
        "num": 46,
        "pourcentage": 0,
        "vote": 0,
        "name": "قائمة حزب التحالف الوطني للسلم والنماء"
      },
      {
        "num": 19,
        "pourcentage": 0.6200000047683716,
        "vote": 4,
        "name": "قائمة كلمة الشعب"
      },
      {
        "num": 47,
        "pourcentage": 0.3100000023841858,
        "vote": 2,
        "name": "قائمة حزب المجد"
      },
      {
        "num": 20,
        "pourcentage": 0.3100000023841858,
        "vote": 2,
        "name": "قائمة دستورنا"
      },
      {
        "num": 48,
        "pourcentage": 2.309999942779541,
        "vote": 15,
        "name": "قائمة حزب المبادرة"
      },
      {
        "num": 21,
        "pourcentage": 0,
        "vote": 0,
        "name": "قائمة الاتحاد الشعبي الجمهوري"
      },
      {
        "num": 49,
        "pourcentage": 1.3799999952316284,
        "vote": 9,
        "name": "قائمة الإرادة والتنمية"
      },
      {
        "num": 22,
        "pourcentage": 0.3100000023841858,
        "vote": 2,
        "name": "قائمة ثوابت الثورة"
      },
      {
        "num": 50,
        "pourcentage": 0,
        "vote": 0,
        "name": "قائمة حلول التنمية"
      },
      {
        "num": 23,
        "pourcentage": 0.15000000596046448,
        "vote": 1,
        "name": "قائمة حركة الشعب الوحدوية التقدمية"
      },
      {
        "num": 51,
        "pourcentage": 0,
        "vote": 0,
        "name": "قائمة حركة الإصلاح والعدالة الاجتماعية"
      },
      {
        "num": 24,
        "pourcentage": 0.46000000834465027,
        "vote": 3,
        "name": "قائمة حزب الإصلاح والتنمية"
      },
      {
        "num": 52,
        "pourcentage": 0.3100000023841858,
        "vote": 2,
        "name": "قائمة حزب الخضر للتقدم (الخضر)"
      },
      {
        "num": 25,
        "pourcentage": 0.7699999809265137,
        "vote": 5,
        "name": "قائمة الوحدة الوطنية"
      },
      {
        "num": 53,
        "pourcentage": 0.6200000047683716,
        "vote": 4,
        "name": "قائمة اتحاد نابل"
      },
      {
        "num": 26,
        "pourcentage": 0.15000000596046448,
        "vote": 1,
        "name": "قائمة المستقلون للشباب أصحاب الكفاءات والشهائد"
      },
      {
        "num": 54,
        "pourcentage": 0.15000000596046448,
        "vote": 1,
        "name": "قائمة حركة الفضيلة"
      },
      {
        "num": 27,
        "pourcentage": 3.690000057220459,
        "vote": 24,
        "name": "قائمة الحزب الديمقراطي التقدمي"
      }
    ],
    "bulletins": {
      "endommage": 0,
      "dans_urne": 678,
      "correct": 650,
      "non_utilise": 222,
      "delivre": 900,
      "blancs": 20,
      "annule": 8
    },
    "electeurs": {
      "votant": 678,
      "enregistre": 827
    }
  }
}