{
  "delegation": {
    "name": "بنزرت الشمالية",
    "code": "51"
  },
  "circonscription": {
    "name": "بنزرت",
    "code": "170"
  },
  "bureau_vote": {
    "name": "قاعة 3",
    "code": "03"
  },
  "centre_vote": {
    "name": "م إعدادية النموذجية  فرحات حشاد بنزرت*",
    "code": "093"
  },
  "resultat": {
    "listes": [
      {
        "num": 28,
        "pourcentage": 0.6499999761581421,
        "vote": 2,
        "name": "قائمة حركة الشعب"
      },
      {
        "num": 1,
        "pourcentage": 0.3199999928474426,
        "vote": 1,
        "name": "قائمة الخضر"
      },
      {
        "num": 29,
        "pourcentage": 0.3199999928474426,
        "vote": 1,
        "name": "قائمة التآلف الجمهوري"
      },
      {
        "num": 2,
        "pourcentage": 0.6499999761581421,
        "vote": 2,
        "name": "-قائمة الإتلاف الديمقراطي المستقل - طريق السلامة"
      },
      {
        "num": 30,
        "pourcentage": 0,
        "vote": 0,
        "name": "قائمة الطريق الثالث"
      },
      {
        "num": 3,
        "pourcentage": 1.940000057220459,
        "vote": 6,
        "name": "قائمة الغد"
      },
      {
        "num": 31,
        "pourcentage": 0,
        "vote": 0,
        "name": "القائمة المستقلة الوحدة الوطنية"
      },
      {
        "num": 4,
        "pourcentage": 0.3199999928474426,
        "vote": 1,
        "name": "قائمة الجلاء"
      },
      {
        "num": 32,
        "pourcentage": 2.5799999237060547,
        "vote": 8,
        "name": "قائمة القطب الديمقراطي الحداثي"
      },
      {
        "num": 5,
        "pourcentage": 0,
        "vote": 0,
        "name": "قائمة الوفاء"
      },
      {
        "num": 33,
        "pourcentage": 0,
        "vote": 0,
        "name": "قائمة الحوار"
      },
      {
        "num": 6,
        "pourcentage": 0,
        "vote": 0,
        "name": "قائمة حركة الوحدويين الأحرار"
      },
      {
        "num": 34,
        "pourcentage": 0.6499999761581421,
        "vote": 2,
        "name": "قائمة المستقلون للشباب أصحاب الكفاءات والشهائد"
      },
      {
        "num": 7,
        "pourcentage": 0,
        "vote": 0,
        "name": "قائمة الكرامة والحرية"
      },
      {
        "num": 35,
        "pourcentage": 0.9700000286102295,
        "vote": 3,
        "name": "قائمة الحزب الليبرالي المغاربي"
      },
      {
        "num": 8,
        "pourcentage": 0.6499999761581421,
        "vote": 2,
        "name": "قائمة حزب التحالف من أجل تونس"
      },
      {
        "num": 36,
        "pourcentage": 0.3199999928474426,
        "vote": 1,
        "name": "قائمة العدل أساس العمران للعدل سنؤسس"
      },
      {
        "num": 9,
        "pourcentage": 0.3199999928474426,
        "vote": 1,
        "name": "قائمة الكرامة"
      },
      {
        "num": 37,
        "pourcentage": 0.3199999928474426,
        "vote": 1,
        "name": "قائمة المستقلة"
      },
      {
        "num": 10,
        "pourcentage": 0,
        "vote": 0,
        "name": "قائمة إئتلاف الأمة"
      },
      {
        "num": 38,
        "pourcentage": 0,
        "vote": 0,
        "name": "القائمة المستقلة شغل حرية كرامة عدالة"
      },
      {
        "num": 11,
        "pourcentage": 0,
        "vote": 0,
        "name": "قائمة الوفاء والصمود"
      },
      {
        "num": 39,
        "pourcentage": 0,
        "vote": 0,
        "name": "قائمة من أجل التوازن بين الجهات"
      },
      {
        "num": 12,
        "pourcentage": 0,
        "vote": 0,
        "name": "قائمة حزب الكرامة والعمل"
      },
      {
        "num": 40,
        "pourcentage": 0,
        "vote": 0,
        "name": "قائمة بنزرت الأم"
      },
      {
        "num": 13,
        "pourcentage": 0.9700000286102295,
        "vote": 3,
        "name": "قائمة الإتحاد الوطني الحر"
      },
      {
        "num": 41,
        "pourcentage": 0.3199999928474426,
        "vote": 1,
        "name": "قائمة الإتحاد الشعبي الجمهوري"
      },
      {
        "num": 14,
        "pourcentage": 0,
        "vote": 0,
        "name": "قائمة حزب الأمة الديمقراطي الإجتماعي"
      },
      {
        "num": 42,
        "pourcentage": 50,
        "vote": 155,
        "name": "قائمة حزب حركة النهضة"
      },
      {
        "num": 15,
        "pourcentage": 0,
        "vote": 0,
        "name": "قائمة جمعية بنزرت للانطلاق والتحدي"
      },
      {
        "num": 43,
        "pourcentage": 1.6100000143051147,
        "vote": 5,
        "name": "قائمة حزب آفاق تونس"
      },
      {
        "num": 16,
        "pourcentage": 0,
        "vote": 0,
        "name": "قائمة  يزينا قهر,,, يزينا حقرة"
      },
      {
        "num": 44,
        "pourcentage": 0.3199999928474426,
        "vote": 1,
        "name": "قائمة الجبهة التقدمية الوطنية"
      },
      {
        "num": 17,
        "pourcentage": 6.449999809265137,
        "vote": 20,
        "name": "قائمة الحزب الديمقراطي التقدمي"
      },
      {
        "num": 45,
        "pourcentage": 0.3199999928474426,
        "vote": 1,
        "name": "قائمة الإتحاد الديمقراطي الوحدوي"
      },
      {
        "num": 18,
        "pourcentage": 2.259999990463257,
        "vote": 7,
        "name": "قائمة العريضة الشعبية للحرية والعدالة والتنمية"
      },
      {
        "num": 46,
        "pourcentage": 6.769999980926514,
        "vote": 21,
        "name": "قائمة حزب التكتل"
      },
      {
        "num": 19,
        "pourcentage": 0.9700000286102295,
        "vote": 3,
        "name": "قائمة دستورنا"
      },
      {
        "num": 47,
        "pourcentage": 0,
        "vote": 0,
        "name": "قائمة من أجل غد أفضل"
      },
      {
        "num": 20,
        "pourcentage": 16.770000457763672,
        "vote": 52,
        "name": "قائمة حزب المؤتمر من أجل الجمهورية"
      },
      {
        "num": 48,
        "pourcentage": 0,
        "vote": 0,
        "name": "قائمة النضال الإجتماعي"
      },
      {
        "num": 21,
        "pourcentage": 0.6499999761581421,
        "vote": 2,
        "name": "قائمة التوازن والعدالة والمصالحة"
      },
      {
        "num": 49,
        "pourcentage": 0,
        "vote": 0,
        "name": "قائمة حركة الديمقراطيين الإشتراكيين"
      },
      {
        "num": 22,
        "pourcentage": 0,
        "vote": 0,
        "name": "قائمة من أجل جبهة وطنية تونسية"
      },
      {
        "num": 50,
        "pourcentage": 0,
        "vote": 0,
        "name": "قائمة البديل"
      },
      {
        "num": 23,
        "pourcentage": 0,
        "vote": 0,
        "name": "قائمة حركة الوحدة الشعبية"
      },
      {
        "num": 51,
        "pourcentage": 0.3199999928474426,
        "vote": 1,
        "name": "قائمة المنارة"
      },
      {
        "num": 24,
        "pourcentage": 0.3199999928474426,
        "vote": 1,
        "name": "قائمة إشكل"
      },
      {
        "num": 52,
        "pourcentage": 0,
        "vote": 0,
        "name": "قائمة  العمل الديمقراطي الجمهوري"
      },
      {
        "num": 25,
        "pourcentage": 0.3199999928474426,
        "vote": 1,
        "name": "قائمة الوحدة الوطنية بنزرت"
      },
      {
        "num": 53,
        "pourcentage": 1.6100000143051147,
        "vote": 5,
        "name": "قائمة حزب العمال الشيوعي التونسي (البديل الثوري)"
      },
      {
        "num": 26,
        "pourcentage": 0,
        "vote": 0,
        "name": "قائمة حزب الوفاق الجمهوري"
      },
      {
        "num": 54,
        "pourcentage": 0,
        "vote": 0,
        "name": "قائمة حركة الشعب الوحدوية التقدمية"
      },
      {
        "num": 27,
        "pourcentage": 0,
        "vote": 0,
        "name": "قائمة حزب الإصلاح والتنمية"
      }
    ],
    "bulletins": {
      "endommage": 0,
      "dans_urne": 314,
      "correct": 310,
      "non_utilise": 696,
      "delivre": 1010,
      "blancs": 2,
      "annule": 2
    },
    "electeurs": {
      "votant": 314,
      "enregistre": 2481
    }
  }
}